{
  "id": "http://example.com/example.json",
  "type": "object",
  "definitions": {},
  "schema": "http://json-schema.org/draft-06/schema#",
  "properties": {
    "data": {
      "id": "/properties/data",
      "type": "object",
      "properties": {
        "cover_image": {
          "id": "/properties/data/properties/cover_image",
          "type": "object",
          "properties": {
            "desktop": {
              "id": "/properties/data/properties/cover_image/properties/desktop",
              "type": "string",
              "title": "Desktop Cover Image"
            },
            "mobile": {
              "id": "/properties/data/properties/cover_image/properties/mobile",
              "type": "string",
              "title": "Mobile Cover Image"
            }
          }
        },
        "map_info": {
          "id": "/properties/data/properties/map_info",
          "type": "object",
          "properties": {
            "distance": {
              "id": "/properties/data/properties/map_info/properties/distance",
              "type": "string",
              "title": "Distance"
            },
            "line_1_text": {
              "id": "/properties/data/properties/map_info/properties/line_1_text",
              "type": "string",
              "title": "White Line Text"
            },
            "line_1_time": {
              "id": "/properties/data/properties/map_info/properties/line_1_time",
              "type": "string",
              "title": "White Line Time"
            },
            "line_2_text": {
              "id": "/properties/data/properties/map_info/properties/line_2_text",
              "type": "string",
              "title": "Green Line Text"
            },
            "line_2_time": {
              "id": "/properties/data/properties/map_info/properties/line_2_time",
              "type": "string",
              "title": "Green Line Time"
            },
            "description": {
              "id": "/properties/data/properties/description",
              "type": "string",
              "title": "Description"
            }
          }
        }
      }
    }
  }
}